ontology/__init__.py
ontology/sdk.py
ontology/account/__init__.py
ontology/account/account.py
ontology/claim/__init__.py
ontology/claim/claim.py
ontology/claim/header.py
ontology/claim/payload.py
ontology/claim/proof.py
ontology/common/__init__.py
ontology/common/address.py
ontology/common/define.py
ontology/common/wallet_qr.py
ontology/contract/__init__.py
ontology/contract/native/__init__.py
ontology/contract/native/aio_asset.py
ontology/contract/native/aio_ong.py
ontology/contract/native/aio_ont.py
ontology/contract/native/aio_ontid.py
ontology/contract/native/asset.py
ontology/contract/native/ong.py
ontology/contract/native/ont.py
ontology/contract/native/ontid.py
ontology/contract/native/vm.py
ontology/contract/neo/__init__.py
ontology/contract/neo/aio_oep4.py
ontology/contract/neo/claim_record.py
ontology/contract/neo/invoke_function.py
ontology/contract/neo/oep4.py
ontology/contract/neo/oep5.py
ontology/contract/neo/vm.py
ontology/contract/neo/abi/__init__.py
ontology/contract/neo/abi/abi_event.py
ontology/contract/neo/abi/abi_function.py
ontology/contract/neo/abi/abi_info.py
ontology/contract/neo/abi/build_params.py
ontology/contract/neo/abi/parameter.py
ontology/contract/neo/abi/struct_type.py
ontology/core/__init__.py
ontology/core/deploy_transaction.py
ontology/core/invoke_transaction.py
ontology/core/program.py
ontology/core/program_info.py
ontology/core/sig.py
ontology/core/transaction.py
ontology/crypto/__init__.py
ontology/crypto/aes_handler.py
ontology/crypto/curve.py
ontology/crypto/digest.py
ontology/crypto/ecies.py
ontology/crypto/hd_key.py
ontology/crypto/hd_private_key.py
ontology/crypto/hd_public_key.py
ontology/crypto/kdf.py
ontology/crypto/key_type.py
ontology/crypto/mnemonic.py
ontology/crypto/scrypt.py
ontology/crypto/signature.py
ontology/crypto/signature_handler.py
ontology/crypto/signature_scheme.py
ontology/exception/__init__.py
ontology/exception/error_code.py
ontology/exception/exception.py
ontology/io/__init__.py
ontology_python_sdk-2.0.6.dist-info/LICENSE
ontology_python_sdk-2.0.6.dist-info/METADATA
ontology_python_sdk-2.0.6.dist-info/WHEEL
ontology_python_sdk-2.0.6.dist-info/top_level.txt
ontology_python_sdk-2.0.6.dist-info/RECORD
