Metadata-Version: 2.1
Name: ontology-python-sdk
Version: 2.0.6
Summary: Comprehensive Python library for the Ontology BlockChain.
Home-page: https://github.com/ontio/ontology-python-sdk
Author: Ontology
Author-email: contact@ont.io
Maintainer: NashMiao
Maintainer-email: wdx7266@outlook.com
License: GNU Lesser General Public License v3 (LGPLv3)
Platform: all
Classifier: Development Status :: 4 - Beta
Classifier: Operating System :: OS Independent
Classifier: Intended Audience :: Developers
Classifier: License :: OSI Approved :: GNU Lesser General Public License v3 (LGPLv3)
Classifier: Programming Language :: Python :: 3.6
Classifier: Programming Language :: Python :: 3.7
Classifier: Programming Language :: Python :: 3.8
Requires-Python: >=3.6
Requires-Dist: aiohttp (>=3.5.4)
Requires-Dist: base58 (>=1.0.3)
Requires-Dist: cryptography (>=2.6.1)
Requires-Dist: ecdsa (>=0.13)
Requires-Dist: mnemonic (>=0.18)
Requires-Dist: pycryptodomex (>=3.7)
Requires-Dist: requests (>=2.21.0)
Requires-Dist: websockets (>=7.0)
